{
    "random_pfd": [
        0.1027,
        0.2061,
        0.3141,
        0.4144,
        0.5087,
        0.6046,
        0.7042,
        0.8015,
        0.9057,
        1.0
    ],
    "deepGini_pfd": [
        0.197,
        0.3825,
        0.5316,
        0.6684,
        0.7947,
        0.889,
        0.9498,
        0.9787,
        0.9962,
        1.0
    ],
    "vanillasoftmax_pfd": [
        0.2061,
        0.3901,
        0.5452,
        0.6821,
        0.7947,
        0.8913,
        0.9498,
        0.9787,
        0.9962,
        1.0
    ],
    "pcs_pfd": [
        0.203,
        0.3871,
        0.5536,
        0.6821,
        0.7954,
        0.8935,
        0.9483,
        0.9787,
        0.9962,
        1.0
    ],
    "entropy_pfd": [
        0.1863,
        0.3612,
        0.5087,
        0.6525,
        0.7757,
        0.873,
        0.9468,
        0.9772,
        0.9954,
        1.0
    ],
    "lgb_pfd": [
        0.251,
        0.4814,
        0.676,
        0.8175,
        0.9156,
        0.9688,
        0.9939,
        0.9985,
        1.0,
        1.0
    ],
    "xgb_pfd": [
        0.251,
        0.4753,
        0.6738,
        0.8304,
        0.9133,
        0.9696,
        0.9939,
        0.9985,
        1.0,
        1.0
    ],
    "rf_pfd": [
        0.2479,
        0.4532,
        0.6357,
        0.7741,
        0.8814,
        0.9422,
        0.981,
        0.9947,
        0.9985,
        1.0
    ],
    "lr_pfd": [
        0.2395,
        0.4548,
        0.6411,
        0.7878,
        0.889,
        0.9544,
        0.9817,
        0.9954,
        0.9992,
        1.0
    ]
}